d2y/__init__.py
d2y/enums.py
d2y/formulas.py
d2y/models.py
d2y/sdk.py
d2y/models/__init__.py
d2y/models/asset.py
d2y/models/option.py
d2y/models/order.py
d2y/models/position.py
d2y/models/simple_option.py
d2y/models/trade.py
d2y/models/user.py
tests/__init__.py
tests/test_formulas.py
tests/test_sdk.py
d2y-0.2.24.dist-info/METADATA
d2y-0.2.24.dist-info/WHEEL
d2y-0.2.24.dist-info/top_level.txt
d2y-0.2.24.dist-info/RECORD
