Metadata-Version: 2.1
Name: d2y
Version: 0.2.24
Summary: A Python SDK for the D2Y Exchange API
Home-page: 
Author: d2y Core Team
Author-email: admin@d2y.exchange
Classifier: Development Status :: 3 - Alpha
Classifier: Intended Audience :: Developers
Classifier: License :: OSI Approved :: MIT License
Classifier: Operating System :: OS Independent
Classifier: Programming Language :: Python
Classifier: Programming Language :: Python :: 3.9
Classifier: Programming Language :: Python :: 3.10
Classifier: Programming Language :: Python :: 3.11
Requires-Python: >=3.9
Requires-Dist: requests
